ua_parser_py-1.0.37.data/data/license.md
ua_parser_py-1.0.37.data/data/readme.md
uaparser/__init__.py
uaparser/_uaparser.py
ua_parser_py-1.0.37.dist-info/METADATA
ua_parser_py-1.0.37.dist-info/WHEEL
ua_parser_py-1.0.37.dist-info/top_level.txt
ua_parser_py-1.0.37.dist-info/RECORD
