Metadata-Version: 2.1
Name: ua-parser-py
Version: 1.0.37
Summary: Python library to detect Browser, Engine, OS, CPU, and Device type/model from User-Agent data
Home-page: https://github.com/vitalibo/ua-parser-py
Author: Vitaliy Boyarsky
Author-email: boyarsky.vitaliy@live.com
License: MIT
Keywords: user-agent parser browser engine os device cpu
Platform: any
Classifier: Environment :: Web Environment
Classifier: Intended Audience :: Developers
Classifier: License :: OSI Approved :: MIT License
Classifier: Operating System :: OS Independent
Classifier: Programming Language :: Python
Classifier: Programming Language :: Python :: 3.6
Classifier: Programming Language :: Python :: 3.7
Classifier: Programming Language :: Python :: 3.8
Classifier: Programming Language :: Python :: 3.9
Classifier: Programming Language :: Python :: 3.10
Classifier: Programming Language :: Python :: Implementation :: CPython
Classifier: Programming Language :: Python :: Implementation :: PyPy
Classifier: Topic :: Internet :: WWW/HTTP
Classifier: Topic :: Software Development :: Libraries :: Python Modules
Requires-Python: >=3.6
